Metadata-Version: 2.1
Name: visrl
Version: 0.1.4
Summary: A simple wrapper to analyse and visualise reinforcement learning agents' behaviour in the environment.
Home-page: https://github.com/jetnew/rl-debugger
Author: Jet New
Author-email: notesjet@gmail.com
License: MIT
Platform: UNKNOWN
Classifier: Development Status :: 1 - Planning
Classifier: Intended Audience :: Science/Research
Classifier: License :: OSI Approved :: MIT License
Classifier: Natural Language :: English
Classifier: Operating System :: OS Independent
Classifier: Programming Language :: Python :: 3
License-File: LICENSE
